{
  "orders": [
    {
      "order": "Q202601010008",
      "project": "杨太新村建设工程项目（一期）",
      "contract": "",
      "payment": "",
      "has_agent": "否",
      "invoice_unit": "",
      "invoice_unit2": "",
      "times": 1,
      "car_volume": 41.472,
      "total_volume": 41.472,
      "price": "",
      "car_amount": 0.0,
      "total_project_amount": 0.0,
      "paid": 0.0,
      "unpaid": 0.0
    },
    {
      "order": "Q202601150004",
      "project": "杨太新村建设工程项目（一期）",
      "contract": "",
      "payment": "",
      "has_agent": "否",
      "invoice_unit": "",
      "invoice_unit2": "",
      "times": 2,
      "car_volume": 41.472,
      "total_volume": 82.944,
      "price": "",
      "car_amount": 0.0,
      "total_project_amount": 0.0,
      "paid": 0.0,
      "unpaid": 0.0
    },
    {
      "order": "Q202601150011",
      "project": "杨太新村建设工程项目（一期）",
      "contract": "",
      "payment": "",
      "has_agent": "否",
      "invoice_unit": "",
      "invoice_unit2": "",
      "times": 3,
      "car_volume": 41.472,
      "total_volume": 124.416,
      "price": "",
      "car_amount": 0.0,
      "total_project_amount": 0.0,
      "paid": 0.0,
      "unpaid": 0.0
    },
    {
      "order": "Q202603090009",
      "project": "杨太新村建设工程项目（一期）",
      "contract": "",
      "payment": "",
      "has_agent": "否",
      "invoice_unit": "",
      "invoice_unit2": "",
      "times": 4,
      "car_volume": 41.472,
      "total_volume": 165.888,
      "price": "180",
      "car_amount": 7464.96,
      "total_project_amount": 7464.96,
      "paid": 0.0,
      "unpaid": 7464.96
    },
    {
      "order": "Q202603110024",
      "project": "杨太新村建设工程项目（一期）",
      "contract": "",
      "payment": "",
      "has_agent": "否",
      "invoice_unit": "",
      "invoice_unit2": "",
      "times": 5,
      "car_volume": 41.472,
      "total_volume": 207.36,
      "price": "180",
      "car_amount": 7464.96,
      "total_project_amount": 14929.92,
      "paid": 0.0,
      "unpaid": 14929.92
    },
    {
      "order": "Q202603150004",
      "project": "杨太新村建设工程项目（一期）",
      "contract": "",
      "payment": "",
      "has_agent": "否",
      "invoice_unit": "",
      "invoice_unit2": "",
      "times": 6,
      "car_volume": 41.472,
      "total_volume": 248.832,
      "price": "180",
      "car_amount": 7464.96,
      "total_project_amount": 22394.88,
      "paid": 0.0,
      "unpaid": 22394.88
    }
  ]
}